headless_waf_builder/__init__.py
headless_waf_builder/apps.py
headless_waf_builder/constants.py
headless_waf_builder/utils.py
headless_waf_builder/wagtail_hooks.py
headless_waf_builder/api/__init__.py
headless_waf_builder/api/router.py
headless_waf_builder/api/schemas.py
headless_waf_builder/api/tasks.py
headless_waf_builder/blocks/__init__.py
headless_waf_builder/blocks/base_static_block.py
headless_waf_builder/blocks/inline_form_block.py
headless_waf_builder/blocks/fields/__init__.py
headless_waf_builder/blocks/fields/base_field_block.py
headless_waf_builder/blocks/fields/blank_condition_block.py
headless_waf_builder/blocks/fields/checkbox_field_block.py
headless_waf_builder/blocks/fields/checkboxes_field_block.py
headless_waf_builder/blocks/fields/condition_block.py
headless_waf_builder/blocks/fields/conditional_block.py
headless_waf_builder/blocks/fields/dropdown_field_block.py
headless_waf_builder/blocks/fields/email_field_block.py
headless_waf_builder/blocks/fields/hidden_field_block.py
headless_waf_builder/blocks/fields/html_field_block.py
headless_waf_builder/blocks/fields/multi_line_field_block.py
headless_waf_builder/blocks/fields/multiselect_field_block.py
headless_waf_builder/blocks/fields/number_field_block.py
headless_waf_builder/blocks/fields/phone_field_block.py
headless_waf_builder/blocks/fields/radio_field_block.py
headless_waf_builder/blocks/fields/simpledate_field_block.py
headless_waf_builder/blocks/fields/single_line_field_block.py
headless_waf_builder/blocks/fields/url_field_block.py
headless_waf_builder/forms/__init__.py
headless_waf_builder/forms/advanced_form_builder.py
headless_waf_builder/forms/widgets/__init__.py
headless_waf_builder/forms/widgets/checkbox_input_widget.py
headless_waf_builder/forms/widgets/custom_select.py
headless_waf_builder/forms/widgets/html_output_widget.py
headless_waf_builder/forms/widgets/side_by_side_checkbox_select_multiple_widget.py
headless_waf_builder/forms/widgets/side_by_side_radio_select_widget.py
headless_waf_builder-1.0.0.dist-info/licenses/LICENCE
headless_waf_builder-1.0.0.dist-info/METADATA
headless_waf_builder-1.0.0.dist-info/WHEEL
headless_waf_builder-1.0.0.dist-info/top_level.txt
headless_waf_builder-1.0.0.dist-info/RECORD
