Metadata-Version: 2.4
Name: headless-waf-builder
Version: 1.0.0
Summary: Headless Wagtail Advanced Form Builder - Complete REST API for modern frontend frameworks
Author-email: "Richard Blake (Octave)" <richard.blake@octave.nz>, "Dan Brosnan (Octave)" <dan.brosnan@octave.nz>, "Vincent Tran (Octave)" <vincent@octave.nz>
Maintainer-email: "Richard Blake (Octave)" <richard.blake@octave.nz>, "Dan Brosnan (Octave)" <dan.brosnan@octave.nz>, "Vincent Tran (Octave)" <vincent@octave.nz>
License: BSD
Project-URL: Homepage, https://github.com/octavenz/headless-waf-builder
Project-URL: Documentation, https://octavenz.github.io/headless-waf-builder/
Project-URL: Repository, https://github.com/octavenz/headless-waf-builder
Project-URL: Bug Tracker, https://github.com/octavenz/headless-waf-builder/issues
Project-URL: Changelog, https://github.com/octavenz/headless-waf-builder/blob/main/CHANGELOG.md
Keywords: wagtail,django,forms,headless,cms,api,rest
Classifier: Development Status :: 5 - Production/Stable
Classifier: Intended Audience :: Developers
Classifier: License :: OSI Approved :: BSD License
Classifier: Operating System :: OS Independent
Classifier: Programming Language :: Python
Classifier: Programming Language :: Python :: 3
Classifier: Programming Language :: Python :: 3.8
Classifier: Programming Language :: Python :: 3.9
Classifier: Programming Language :: Python :: 3.10
Classifier: Programming Language :: Python :: 3.11
Classifier: Programming Language :: Python :: 3.12
Classifier: Framework :: Django :: 4.2
Classifier: Framework :: Django :: 5.0
Classifier: Framework :: Wagtail :: 6
Classifier: Topic :: Internet :: WWW/HTTP :: Dynamic Content :: Content Management System
Classifier: Topic :: Software Development :: Libraries :: Python Modules
Requires-Python: >=3.8
License-File: LICENCE
Requires-Dist: Django>=4.2
Requires-Dist: Wagtail>=6.4
Requires-Dist: wagtailextraicons
Requires-Dist: django-ninja
Requires-Dist: pydantic>=2.0
Requires-Dist: psycopg[binary]
Requires-Dist: django-recaptcha
Requires-Dist: celery
Requires-Dist: redis
Provides-Extra: dev
Requires-Dist: django-extensions; extra == "dev"
Requires-Dist: pytest; extra == "dev"
Requires-Dist: pytest-django; extra == "dev"
Requires-Dist: pytest-cov; extra == "dev"
Requires-Dist: black; extra == "dev"
Requires-Dist: isort; extra == "dev"
Requires-Dist: flake8; extra == "dev"
Requires-Dist: pre-commit; extra == "dev"
Requires-Dist: mkdocs; extra == "dev"
Requires-Dist: mkdocs-material; extra == "dev"
Provides-Extra: test
Requires-Dist: pytest; extra == "test"
Requires-Dist: pytest-django; extra == "test"
Requires-Dist: pytest-cov; extra == "test"
Requires-Dist: coverage; extra == "test"
Dynamic: license-file
